dbforge/cli.py
dbforge/version.yaml
dbforge/databases/commands/pg_cmds.py
dbforge/databases/postgres/pg.py
dbforge/system/dbforge_docker.py
dbforge/system/dbforge_help.py
dbforge-2.2.19.dist-info/METADATA
dbforge-2.2.19.dist-info/WHEEL
dbforge-2.2.19.dist-info/entry_points.txt
dbforge-2.2.19.dist-info/RECORD
